easycrop/__init__.py
easycrop/cli.py
easycrop/crop.py
easycrop-0.0.3.dist-info/METADATA
easycrop-0.0.3.dist-info/WHEEL
easycrop-0.0.3.dist-info/entry_points.txt
easycrop-0.0.3.dist-info/licenses/LICENSE
easycrop-0.0.3.dist-info/RECORD
