Metadata-Version: 2.3
Name: easycrop
Version: 0.0.3
Summary: Easy image Cropper CLI.
Project-URL: Homepage, https://github.com/moutella/crop
Project-URL: Issues, https://github.com/moutella/crop/issues
Author-email: moutella <joaogabrielmsc@gmail.com>
License-File: LICENSE
Classifier: License :: OSI Approved :: MIT License
Classifier: Operating System :: OS Independent
Classifier: Programming Language :: Python :: 3
Requires-Python: >=3.8
Requires-Dist: pillow
